mkdocs_asciinema_player/__init__.py
mkdocs_asciinema_player/assets/asciinema-player.css
mkdocs_asciinema_player/assets/asciinema-player.min.js
mkdocs_asciinema_player/assets/icons/close.svg
mkdocs_asciinema_player/assets/icons/maximize.svg
mkdocs_asciinema_player/assets/icons/minimize.svg
mkdocs_asciinema_player/assets/terminal-player.css
mkdocs_asciinema_player/plugin.py
mkdocs_asciinema_player/templates/asciinema-player.html
mkdocs_asciinema_player/templates/themes/blue.html
mkdocs_asciinema_player/templates/themes/night.html
mkdocs_asciinema_player/templates/themes/none.html
mkdocs_asciinema_player/templates/themes/penguin.html
mkdocs_asciinema_player-0.20.0.dist-info/WHEEL
mkdocs_asciinema_player-0.20.0.dist-info/entry_points.txt
mkdocs_asciinema_player-0.20.0.dist-info/METADATA
mkdocs_asciinema_player-0.20.0.dist-info/RECORD
