Metadata-Version: 2.4
Name: mkdocs-asciinema-player
Version: 0.20.0
Summary: A Mkdocs Plugin to include asciinema player in your documentation.
Keywords: mkdocs,documentation,asciinema,asciinema-player
Author: Philippe-André De Carvalho
Author-email: Philippe-André De Carvalho <philippe.andre.decarvalho@gmail.com>
License-Expression: MIT
Classifier: Development Status :: 5 - Production/Stable
Classifier: Environment :: Console
Classifier: Operating System :: POSIX
Classifier: Intended Audience :: Developers
Classifier: Intended Audience :: Information Technology
Classifier: Intended Audience :: System Administrators
Classifier: Topic :: Software Development :: Build Tools
Classifier: Natural Language :: English
Classifier: Programming Language :: Python :: 3.10
Classifier: Programming Language :: Python :: 3.11
Classifier: Programming Language :: Python :: 3.12
Classifier: Programming Language :: Python :: 3.13
Classifier: Programming Language :: Python :: 3.14
Classifier: Topic :: Utilities
Classifier: Topic :: Software Development :: Documentation
Requires-Dist: mkdocs>=1.6.1,<2
Maintainer: Philippe-André De Carvalho
Maintainer-email: Philippe-André De Carvalho <philippe.andre.decarvalho@gmail.com>
Requires-Python: >=3.10, <4
Project-URL: documentation, https://pa-decarvalho.github.io/mkdocs-asciinema-player
Project-URL: homepage, https://github.com/pa-decarvalho/mkdocs-asciinema-player
Project-URL: repository, https://github.com/pa-decarvalho/mkdocs-asciinema-player
